pymas/agent/__pycache__/agent.cpython-312.pyc
pymas/agent/__pycache__/baseagent.cpython-312.pyc
pymas/agent/agent.py
pymas/agent/agent_prompt.py
pymas/agent/baseagent.py
pymas/crew/crew.py
pymas/llm/__pycache__/constants.cpython-312.pyc
pymas/llm/__pycache__/llm.cpython-312.pyc
pymas/llm/constants.py
pymas/llm/llm.py
pymas/messages/__pycache__/assistant.cpython-312.pyc
pymas/messages/__pycache__/base.cpython-312.pyc
pymas/messages/__pycache__/system.cpython-312.pyc
pymas/messages/__pycache__/user.cpython-312.pyc
pymas/messages/assistant.py
pymas/messages/base.py
pymas/messages/system.py
pymas/messages/user.py
pymas2-0.1.1.dist-info/METADATA
pymas2-0.1.1.dist-info/WHEEL
pymas2-0.1.1.dist-info/RECORD
