Metadata-Version: 2.3
Name: pymas2
Version: 0.1.1
Summary: Multiagent Framework
Author: contact@bayeslabs.co
Requires-Python: >=3.10,<4.0
Classifier: Programming Language :: Python :: 3
Classifier: Programming Language :: Python :: 3.10
Classifier: Programming Language :: Python :: 3.11
Classifier: Programming Language :: Python :: 3.12
Classifier: Programming Language :: Python :: 3.13
Requires-Dist: ipykernel (>=6.29.5,<7.0.0)
Requires-Dist: litellm (>=1.57.2,<2.0.0)
Requires-Dist: pydantic (>=2.10.4,<3.0.0)
